omu_ubys/__init__.py
omu_ubys/auth.py
omu_ubys/client.py
omu_ubys/exceptions.py
omu_ubys/models.py
omu_ubys/parsers/__init__.py
omu_ubys/parsers/advisor.py
omu_ubys/parsers/cafeteria.py
omu_ubys/parsers/grades.py
omu_ubys/parsers/profile.py
omu_ubys/parsers/schedule.py
omu_ubys/parsers/transcript.py
omu_ubys-1.0.4.dist-info/METADATA
omu_ubys-1.0.4.dist-info/WHEEL
omu_ubys-1.0.4.dist-info/licenses/LICENSE
omu_ubys-1.0.4.dist-info/RECORD
