Metadata-Version: 2.4
Name: omu-ubys
Version: 1.0.4
Summary: Unofficial Python client for OMU UBYS (University Information Management System)
Project-URL: Homepage, https://github.com/emi-ran/omu-ubys
Project-URL: Documentation, https://github.com/emi-ran/omu-ubys#readme
Project-URL: Repository, https://github.com/emi-ran/omu-ubys
Project-URL: Issues, https://github.com/emi-ran/omu-ubys/issues
Author-email: Emirhan <emirhan551952@gmail.com>
License-Expression: MIT
License-File: LICENSE
Keywords: api,omu,ondokuz-mayis,student,ubys,university,unofficial
Classifier: Development Status :: 3 - Alpha
Classifier: Intended Audience :: Developers
Classifier: Intended Audience :: Education
Classifier: License :: OSI Approved :: MIT License
Classifier: Operating System :: OS Independent
Classifier: Programming Language :: Python :: 3
Classifier: Programming Language :: Python :: 3.9
Classifier: Programming Language :: Python :: 3.10
Classifier: Programming Language :: Python :: 3.11
Classifier: Programming Language :: Python :: 3.12
Classifier: Topic :: Education
Classifier: Topic :: Software Development :: Libraries :: Python Modules
Requires-Python: >=3.9
Requires-Dist: beautifulsoup4>=4.12.0
Requires-Dist: httpx>=0.24.0
Requires-Dist: lxml>=4.9.0
Provides-Extra: dev
Requires-Dist: pytest-cov>=4.0.0; extra == 'dev'
Requires-Dist: pytest>=7.0.0; extra == 'dev'
